{
    "boundary": [
        {
            "start": [
                79.60093896713614,
                64.88262910798122
            ],
            "end": [
                78.47417840375586,
                66.19718309859154
            ],
            "next": null,
            "hole": false
        },
        {
            "start": [
                78.47417840375586,
                66.19718309859154
            ],
            "end": [
                76.97183098591549,
                67.69953051643192
            ],
            "next": null,
            "hole": false
        },
        {
            "start": [
                76.97183098591549,
                67.69953051643192
            ],
            "end": [
                75.28169014084507,
                69.38967136150234
            ],
            "next": null,
            "hole": false
        },
        {
            "start": [
                75.28169014084507,
                69.38967136150234
            ],
            "end": [
                72.46478873239437,
                71.2676056338028
            ],
            "next": null,
            "hole": false
        },
        {
            "start": [
                72.46478873239437,
                71.2676056338028
            ],
            "end": [
                69.64788732394366,
                71.6431924882629
            ],
            "next": null,
            "hole": false
        },
        {
            "start": [
                69.64788732394366,
                71.6431924882629
            ],
            "end": [
                66.26760563380282,
                72.20657276995304
            ],
            "next": null,
            "hole": false
        },
        {
            "start": [
                66.26760563380282,
                72.20657276995304
            ],
            "end": [
                61.57276995305163,
                72.20657276995304
            ],
            "next": null,
            "hole": false
        },
        {
            "start": [
                61.57276995305163,
                72.20657276995304
            ],
            "end": [
                56.69014084507042,
                72.20657276995304
            ],
            "next": null,
            "hole": false
        },
        {
            "start": [
                56.69014084507042,
                72.20657276995304
            ],
            "end": [
                54.436619718309856,
                71.83098591549295
            ],
            "next": null,
            "hole": false
        },
        {
            "start": [
                54.436619718309856,
                71.83098591549295
            ],
            "end": [
                50.68075117370891,
                70.32863849765258
            ],
            "next": null,
            "hole": false
        },
        {
            "start": [
                50.68075117370891,
                70.32863849765258
            ],
            "end": [
                45.4225352112676,
                68.63849765258215
            ],
            "next": null,
            "hole": false
        },
        {
            "start": [
                45.4225352112676,
                68.63849765258215
            ],
            "end": [
                42.98122065727699,
                66.94835680751173
            ],
            "next": null,
            "hole": false
        },
        {
            "start": [
                42.98122065727699,
                66.94835680751173
            ],
            "end": [
                40.915492957746466,
                64.88262910798122
            ],
            "next": null,
            "hole": false
        },
        {
            "start": [
                40.915492957746466,
                64.88262910798122
            ],
            "end": [
                39.037558685446,
                61.69014084507042
            ],
            "next": null,
            "hole": false
        },
        {
            "start": [
                39.037558685446,
                61.69014084507042
            ],
            "end": [
                37.347417840375584,
                58.87323943661971
            ],
            "next": null,
            "hole": false
        },
        {
            "start": [
                37.347417840375584,
                58.87323943661971
            ],
            "end": [
                35.8450704225352,
                55.492957746478865
            ],
            "next": null,
            "hole": false
        },
        {
            "start": [
                35.8450704225352,
                55.492957746478865
            ],
            "end": [
                35.65727699530515,
                52.11267605633802
            ],
            "next": null,
            "hole": false
        },
        {
            "start": [
                35.65727699530515,
                52.11267605633802
            ],
            "end": [
                35.469483568075105,
                48.73239436619717
            ],
            "next": null,
            "hole": false
        },
        {
            "start": [
                35.469483568075105,
                48.73239436619717
            ],
            "end": [
                35.469483568075105,
                45.35211267605632
            ],
            "next": null,
            "hole": false
        },
        {
            "start": [
                35.469483568075105,
                45.35211267605632
            ],
            "end": [
                36.03286384976525,
                41.97183098591549
            ],
            "next": null,
            "hole": false
        },
        {
            "start": [
                36.03286384976525,
                41.97183098591549
            ],
            "end": [
                37.159624413145536,
                40.28169014084506
            ],
            "next": null,
            "hole": false
        },
        {
            "start": [
                37.159624413145536,
                40.28169014084506
            ],
            "end": [
                38.661971830985905,
                38.59154929577464
            ],
            "next": null,
            "hole": false
        },
        {
            "start": [
                38.661971830985905,
                38.59154929577464
            ],
            "end": [
                40.16431924882629,
                37.6525821596244
            ],
            "next": null,
            "hole": false
        },
        {
            "start": [
                40.16431924882629,
                37.6525821596244
            ],
            "end": [
                42.41784037558685,
                35.77464788732394
            ],
            "next": null,
            "hole": false
        },
        {
            "start": [
                42.41784037558685,
                35.77464788732394
            ],
            "end": [
                45.23474178403755,
                35.21126760563379
            ],
            "next": null,
            "hole": false
        },
        {
            "start": [
                45.23474178403755,
                35.21126760563379
            ],
            "end": [
                47.86384976525821,
                34.46009389671361
            ],
            "next": null,
            "hole": false
        },
        {
            "start": [
                47.86384976525821,
                34.46009389671361
            ],
            "end": [
                50.492957746478865,
                34.27230046948356
            ],
            "next": null,
            "hole": false
        },
        {
            "start": [
                50.492957746478865,
                34.27230046948356
            ],
            "end": [
                52.74647887323944,
                33.52112676056337
            ],
            "next": null,
            "hole": false
        },
        {
            "start": [
                52.74647887323944,
                33.52112676056337
            ],
            "end": [
                55.75117370892018,
                33.14553990610328
            ],
            "next": null,
            "hole": false
        },
        {
            "start": [
                55.75117370892018,
                33.14553990610328
            ],
            "end": [
                58.94366197183098,
                33.14553990610328
            ],
            "next": null,
            "hole": false
        },
        {
            "start": [
                58.94366197183098,
                33.14553990610328
            ],
            "end": [
                61.009389671361504,
                33.14553990610328
            ],
            "next": null,
            "hole": false
        },
        {
            "start": [
                61.009389671361504,
                33.14553990610328
            ],
            "end": [
                64.01408450704226,
                33.14553990610328
            ],
            "next": null,
            "hole": false
        },
        {
            "start": [
                64.01408450704226,
                33.14553990610328
            ],
            "end": [
                65.51643192488262,
                33.896713615023465
            ],
            "next": null,
            "hole": false
        },
        {
            "start": [
                65.51643192488262,
                33.896713615023465
            ],
            "end": [
                67.39436619718309,
                35.023474178403745
            ],
            "next": null,
            "hole": false
        },
        {
            "start": [
                67.39436619718309,
                35.023474178403745
            ],
            "end": [
                68.70892018779342,
                35.77464788732394
            ],
            "next": null,
            "hole": false
        },
        {
            "start": [
                68.70892018779342,
                35.77464788732394
            ],
            "end": [
                70.39906103286384,
                37.27699530516431
            ],
            "next": null,
            "hole": false
        },
        {
            "start": [
                70.39906103286384,
                37.27699530516431
            ],
            "end": [
                71.71361502347418,
                38.77934272300469
            ],
            "next": null,
            "hole": false
        },
        {
            "start": [
                71.71361502347418,
                38.77934272300469
            ],
            "end": [
                72.84037558685445,
                40.09389671361501
            ],
            "next": null,
            "hole": false
        },
        {
            "start": [
                72.84037558685445,
                40.09389671361501
            ],
            "end": [
                74.34272300469483,
                41.97183098591549
            ],
            "next": null,
            "hole": false
        },
        {
            "start": [
                74.34272300469483,
                41.97183098591549
            ],
            "end": [
                76.59624413145539,
                42.910798122065714
            ],
            "next": null,
            "hole": false
        },
        {
            "start": [
                76.59624413145539,
                42.910798122065714
            ],
            "end": [
                78.47417840375586,
                44.97652582159624
            ],
            "next": null,
            "hole": false
        },
        {
            "start": [
                78.47417840375586,
                44.97652582159624
            ],
            "end": [
                79.78873239436619,
                46.66666666666666
            ],
            "next": null,
            "hole": false
        },
        {
            "start": [
                79.78873239436619,
                46.66666666666666
            ],
            "end": [
                80.35211267605634,
                48.54460093896712
            ],
            "next": null,
            "hole": false
        },
        {
            "start": [
                80.35211267605634,
                48.54460093896712
            ],
            "end": [
                81.10328638497651,
                50.046948356807505
            ],
            "next": null,
            "hole": false
        },
        {
            "start": [
                81.10328638497651,
                50.046948356807505
            ],
            "end": [
                81.8544600938967,
                51.549295774647874
            ],
            "next": null,
            "hole": false
        },
        {
            "start": [
                81.8544600938967,
                51.549295774647874
            ],
            "end": [
                82.41784037558685,
                53.80281690140845
            ],
            "next": null,
            "hole": false
        },
        {
            "start": [
                82.41784037558685,
                53.80281690140845
            ],
            "end": [
                83.73239436619718,
                56.61971830985915
            ],
            "next": null,
            "hole": false
        },
        {
            "start": [
                83.73239436619718,
                56.61971830985915
            ],
            "end": [
                83.73239436619718,
                58.685446009389665
            ],
            "next": null,
            "hole": false
        },
        {
            "start": [
                83.73239436619718,
                58.685446009389665
            ],
            "end": [
                82.98122065727699,
                61.877934272300465
            ],
            "next": null,
            "hole": false
        },
        {
            "start": [
                82.98122065727699,
                61.877934272300465
            ],
            "end": [
                79.60093896713614,
                64.88262910798122
            ],
            "next": null,
            "hole": false
        }
    ],
    "holes": [],
    "edges": [],
    "disks": [],
    "n": 50,
    "n_corner": 0,
    "n_triangles": 0,
    "n_disks": 0,
    "n_remainder": 0,
    "n_regions": 0
}